README.md
setup.py
insight2.egg-info/PKG-INFO
insight2.egg-info/SOURCES.txt
insight2.egg-info/dependency_links.txt
insight2.egg-info/requires.txt
insight2.egg-info/top_level.txt
magetool/AEStool.py
magetool/HttpServer.py
magetool/NetWorkTest.py
magetool/RSAtool.py
magetool/SocketClientDemo.py
magetool/SocketServerDemo.py
magetool/SystemMsgTool.py
magetool/__init__.py
magetool/dbTool.py
magetool/importFile.py
magetool/klinetool.py
magetool/listtool.py
magetool/okexUtil.py
magetool/pathtool.py
magetool/pytimer.py
magetool/systool.py
magetool/timetool.py
magetool/urltool.py
magetool/uuidTool.py