Metadata-Version: 1.0
Name: insight2
Version: 0.1.36
Summary: time and path tool
Home-page: UNKNOWN
Author: ark1ee
Author-email: ark1ee@ark.com
License: MIT Licence
Keywords: pathtool,timetool,magetool,mage
Platform: any
